fsdtorch/__init__.py
fsdtorch/inference.py
fsdtorch-0.1.2.1.dist-info/WHEEL
fsdtorch-0.1.2.1.dist-info/METADATA
fsdtorch-0.1.2.1.dist-info/RECORD
